{
  "folder_creation": {
    "status": 200,
    "msg": "OK",
    "result": {
      "fld_id": "1184826",
      "code": "kp3smrjtfa",
      "name": "BebyGebb"
    },
    "server_time": "2023-12-24 16:22:10"
  },
  "upload_responses": [
    {
      "msg": "OK",
      "server_time": "2023-12-24 16:22:10",
      "status": 200,
      "result": {
        "embed_url": "https://ds2video.com/e/1pzv1et2dd00",
        "download_url": "https://ds2video.com/d/1pzv1et2dd00",
        "protected_download": "https://ds2video.com/d/obfpzqc4hxjugbhsvtt3vwysoirovxrs",
        "filecode": "1pzv1et2dd00",
        "protected_embed": "https://ds2video.com/e/00rm7fuztsko8gpv89cqfvlrowe09tys"
      }
    },
    {
      "result": {
        "protected_download": "https://ds2video.com/d/8da74rsd3z1q43ijzyxgq5nme73nc56x",
        "filecode": "vj35vmazmsp9",
        "download_url": "https://ds2video.com/d/vj35vmazmsp9",
        "protected_embed": "https://ds2video.com/e/u2x5wjhtpbhfq3k597lyqjx8ta4gbbgv",
        "embed_url": "https://ds2video.com/e/vj35vmazmsp9"
      },
      "server_time": "2023-12-24 16:22:11",
      "msg": "OK",
      "status": 200
    },
    {
      "result": {
        "protected_embed": "https://ds2video.com/e/d8kpulpylbpf2zoyf3p9lw5q3obopilq",
        "protected_download": "https://ds2video.com/d/qp9tktp58fzrcnbygopw9laayginkcdy",
        "filecode": "kaibohlsxr94",
        "embed_url": "https://ds2video.com/e/kaibohlsxr94",
        "download_url": "https://ds2video.com/d/kaibohlsxr94"
      },
      "status": 200,
      "server_time": "2023-12-24 16:22:12",
      "msg": "OK"
    },
    {
      "result": {
        "download_url": "https://ds2video.com/d/7y0j3kj4ienn",
        "protected_embed": "https://ds2video.com/e/ggyn8h6h3te0wm7dgp7xo5zv9h2zhk6s",
        "filecode": "7y0j3kj4ienn",
        "embed_url": "https://ds2video.com/e/7y0j3kj4ienn",
        "protected_download": "https://ds2video.com/d/9lcdqotqj54jwmcewoq3f1s9h4unnx6x"
      },
      "msg": "OK",
      "server_time": "2023-12-24 16:22:13",
      "status": 200
    },
    {
      "msg": "OK",
      "result": {
        "filecode": "zzh9h05j589d",
        "embed_url": "https://ds2video.com/e/zzh9h05j589d",
        "protected_embed": "https://ds2video.com/e/ue0bgebudu7614moz1xpodl4qfyotdmn",
        "protected_download": "https://ds2video.com/d/to3bhxcqivohicwtkdk8avz6sz8rpljc",
        "download_url": "https://ds2video.com/d/zzh9h05j589d"
      },
      "server_time": "2023-12-24 16:22:14",
      "status": 200
    },
    {
      "result": {
        "protected_embed": "https://ds2video.com/e/0ot2w1zel8rykif5w3acinp4ay6f2zfg",
        "protected_download": "https://ds2video.com/d/8pq08e7pzu3eh3w7si84y938s88v606e",
        "download_url": "https://ds2video.com/d/yk1lzul1z6ms",
        "embed_url": "https://ds2video.com/e/yk1lzul1z6ms",
        "filecode": "yk1lzul1z6ms"
      },
      "msg": "OK",
      "server_time": "2023-12-24 16:22:14",
      "status": 200
    },
    {
      "result": {
        "embed_url": "https://ds2video.com/e/14kmzvm1duur",
        "download_url": "https://ds2video.com/d/14kmzvm1duur",
        "protected_embed": "https://ds2video.com/e/nu2svv8g2bzunpmv6l36p2aypewikvs6",
        "filecode": "14kmzvm1duur",
        "protected_download": "https://ds2video.com/d/k0rgycp9xdr1leozx710gk54leffrpnu"
      },
      "status": 200,
      "server_time": "2023-12-24 16:22:15",
      "msg": "OK"
    },
    {
      "result": {
        "download_url": "https://ds2video.com/d/idxvib60opkn",
        "embed_url": "https://ds2video.com/e/idxvib60opkn",
        "protected_download": "https://ds2video.com/d/9a7x4w59p21j6dfbupa6kn3kfc6rvbzz",
        "filecode": "idxvib60opkn",
        "protected_embed": "https://ds2video.com/e/ecygt0w7qcl61cc1tnwzzj304cawn50f"
      },
      "server_time": "2023-12-24 16:22:16",
      "msg": "OK",
      "status": 200
    },
    {
      "status": 200,
      "server_time": "2023-12-24 16:22:17",
      "result": {
        "download_url": "https://ds2video.com/d/273ea1c7ydro",
        "protected_download": "https://ds2video.com/d/0fcl7enfyjt22g6vohxckdwzipqbkw4o",
        "protected_embed": "https://ds2video.com/e/a7vzw14j0ns7f9djftlwsglcww3kmsa0",
        "filecode": "273ea1c7ydro",
        "embed_url": "https://ds2video.com/e/273ea1c7ydro"
      },
      "msg": "OK"
    },
    {
      "result": {
        "filecode": "spx8l5vc0c7x",
        "protected_download": "https://ds2video.com/d/rgatl0arqsr0lmmhbuw0in3cuposutv5",
        "embed_url": "https://ds2video.com/e/spx8l5vc0c7x",
        "download_url": "https://ds2video.com/d/spx8l5vc0c7x",
        "protected_embed": "https://ds2video.com/e/ujus0xz00lpwy3itvoo519s0912gb8q4"
      },
      "msg": "OK",
      "server_time": "2023-12-24 16:22:17",
      "status": 200
    },
    {
      "result": {
        "download_url": "https://ds2video.com/d/b8ghj4gzlzn4",
        "embed_url": "https://ds2video.com/e/b8ghj4gzlzn4",
        "protected_embed": "https://ds2video.com/e/ssj754ptt81oiebh2jn1de6szbdj96ge",
        "protected_download": "https://ds2video.com/d/ycospq43o0q28tq3zzpqc8er8898mpv8",
        "filecode": "b8ghj4gzlzn4"
      },
      "server_time": "2023-12-24 16:22:18",
      "msg": "OK",
      "status": 200
    },
    {
      "msg": "OK",
      "result": {
        "protected_embed": "https://ds2video.com/e/h2at7jtf41yr6bqogai2ig9qf96ed274",
        "filecode": "13swvu8wrug6",
        "download_url": "https://ds2video.com/d/13swvu8wrug6",
        "protected_download": "https://ds2video.com/d/4otdtknljk4tz8qn8xtowlwp5pfvpnkw",
        "embed_url": "https://ds2video.com/e/13swvu8wrug6"
      },
      "server_time": "2023-12-24 16:22:19",
      "status": 200
    },
    {
      "msg": "OK",
      "status": 200,
      "result": {
        "protected_download": "https://ds2video.com/d/73meec80adr5728wm85yge7jm9oc4f4b",
        "filecode": "o3wfoyz8ksga",
        "download_url": "https://ds2video.com/d/o3wfoyz8ksga",
        "protected_embed": "https://ds2video.com/e/z561jotyibnr1y77b1r355ct5zbao4pq",
        "embed_url": "https://ds2video.com/e/o3wfoyz8ksga"
      },
      "server_time": "2023-12-24 16:22:19"
    },
    {
      "status": 200,
      "msg": "OK",
      "result": {
        "protected_embed": "https://ds2video.com/e/4gb8xef3njcidyg2ozkfo33g4o9oz91r",
        "embed_url": "https://ds2video.com/e/rpxsyqo0l990",
        "download_url": "https://ds2video.com/d/rpxsyqo0l990",
        "filecode": "rpxsyqo0l990",
        "protected_download": "https://ds2video.com/d/vv9yta0362k6r8p96d5t30b1ha386m8q"
      },
      "server_time": "2023-12-24 16:22:20"
    },
    {
      "server_time": "2023-12-24 16:22:21",
      "status": 200,
      "msg": "OK",
      "result": {
        "protected_embed": "https://ds2video.com/e/swbetpecipbg5oh36uovj591iv9pi986",
        "embed_url": "https://ds2video.com/e/mrf0sjm3h6z8",
        "filecode": "mrf0sjm3h6z8",
        "download_url": "https://ds2video.com/d/mrf0sjm3h6z8",
        "protected_download": "https://ds2video.com/d/rh8uw6o1ywxh4ycsi8w8ic9kuq2j53u7"
      }
    },
    {
      "status": 200,
      "result": {
        "download_url": "https://ds2video.com/d/k5w0ruyovca3",
        "embed_url": "https://ds2video.com/e/k5w0ruyovca3",
        "protected_embed": "https://ds2video.com/e/lp2yuoicn0v568dn3zf6acy3h3qyvf8h",
        "protected_download": "https://ds2video.com/d/d47thwvyey07a2hngfhr7omgjtpoyfcu",
        "filecode": "k5w0ruyovca3"
      },
      "server_time": "2023-12-24 16:22:22",
      "msg": "OK"
    },
    {
      "server_time": "2023-12-24 16:22:23",
      "result": {
        "protected_embed": "https://ds2video.com/e/bleqqlx9rwur5mpcddspnsfwzh7743ra",
        "download_url": "https://ds2video.com/d/x12bwpfxiph9",
        "protected_download": "https://ds2video.com/d/ri1xmfwhye5uybxqexix96y6jezgqhoj",
        "embed_url": "https://ds2video.com/e/x12bwpfxiph9",
        "filecode": "x12bwpfxiph9"
      },
      "msg": "OK",
      "status": 200
    },
    {
      "result": {
        "protected_download": "https://ds2video.com/d/77bo86l6l3mamjvg8tb5w1q60l4zlt2e",
        "download_url": "https://ds2video.com/d/ufuoscwbpfcx",
        "embed_url": "https://ds2video.com/e/ufuoscwbpfcx",
        "filecode": "ufuoscwbpfcx",
        "protected_embed": "https://ds2video.com/e/n406rkts1k6hq80jzehmamfmh16lxdnz"
      },
      "server_time": "2023-12-24 16:22:24",
      "msg": "OK",
      "status": 200
    },
    {
      "result": {
        "protected_download": "https://ds2video.com/d/958j7lkesndfa64b4nj4pwsthnqgkmb3",
        "filecode": "dwdjqtffr36x",
        "download_url": "https://ds2video.com/d/dwdjqtffr36x",
        "embed_url": "https://ds2video.com/e/dwdjqtffr36x",
        "protected_embed": "https://ds2video.com/e/3aybfhia2s05fxrzp8a282ff5e080byt"
      },
      "server_time": "2023-12-24 16:22:24",
      "status": 200,
      "msg": "OK"
    },
    {
      "result": {
        "protected_download": "https://ds2video.com/d/e43ay4ro49abmt59qp3c6i29zizqvs2g",
        "embed_url": "https://ds2video.com/e/l5ut49nss4sy",
        "filecode": "l5ut49nss4sy",
        "protected_embed": "https://ds2video.com/e/4si3za3mbfjolw7zjx6eaybgte215dtt",
        "download_url": "https://ds2video.com/d/l5ut49nss4sy"
      },
      "msg": "OK",
      "server_time": "2023-12-24 16:22:25",
      "status": 200
    },
    {
      "msg": "OK",
      "result": {
        "protected_download": "https://ds2video.com/d/ekewlgzb9fgbih66torx78yf68t4i33c",
        "embed_url": "https://ds2video.com/e/2ke2u7m23qlm",
        "download_url": "https://ds2video.com/d/2ke2u7m23qlm",
        "filecode": "2ke2u7m23qlm",
        "protected_embed": "https://ds2video.com/e/4ao6pf14rl3eyj7tp1j009it1iu0c8o2"
      },
      "server_time": "2023-12-24 16:22:26",
      "status": 200
    }
  ]
}