{
  "folder_creation": {
    "server_time": "2023-12-26 08:05:11",
    "result": {
      "code": "pkb1601tk5",
      "name": "DIAN FATMALA HIJAB",
      "fld_id": "1187058"
    },
    "status": 200,
    "msg": "OK"
  },
  "upload_responses": [
    {
      "msg": "OK",
      "status": 200,
      "server_time": "2023-12-26 08:05:11",
      "result": {
        "download_url": "https://ds2video.com/d/jkub5z8758s9",
        "protected_embed": "https://ds2video.com/e/m0oqr3t6767srv6xbhn0gl5bldftu1jl",
        "filecode": "jkub5z8758s9",
        "protected_download": "https://ds2video.com/d/hdupd70487yhn4j6bez4wgk7vd0woz2c",
        "embed_url": "https://ds2video.com/e/jkub5z8758s9"
      }
    },
    {
      "result": {
        "download_url": "https://ds2video.com/d/w6swioiz5nl1",
        "embed_url": "https://ds2video.com/e/w6swioiz5nl1",
        "protected_download": "https://ds2video.com/d/qsdhrwmjx27maphzsxmfwwwsls3x69du",
        "protected_embed": "https://ds2video.com/e/aq5dy93dt9ll7ifpsa8tr5rrp8m331bt",
        "filecode": "w6swioiz5nl1"
      },
      "msg": "OK",
      "server_time": "2023-12-26 08:05:12",
      "status": 200
    },
    {
      "msg": "OK",
      "status": 200,
      "result": {
        "download_url": "https://ds2video.com/d/z0htskbhfqum",
        "filecode": "z0htskbhfqum",
        "protected_download": "https://ds2video.com/d/9xg0enbg718nmmkhb7uomt5fh2twwog7",
        "protected_embed": "https://ds2video.com/e/qi1gqc405b93lak4cuy2jghhbrbqglov",
        "embed_url": "https://ds2video.com/e/z0htskbhfqum"
      },
      "server_time": "2023-12-26 08:05:12"
    },
    {
      "status": 200,
      "server_time": "2023-12-26 08:05:12",
      "result": {
        "filecode": "nfr6os3qthtb",
        "protected_download": "https://ds2video.com/d/uapfpw4j4rartbyfy0t89a1xybm00e3r",
        "embed_url": "https://ds2video.com/e/nfr6os3qthtb",
        "download_url": "https://ds2video.com/d/nfr6os3qthtb",
        "protected_embed": "https://ds2video.com/e/ew6q4ny0uajzb1akmvwjt9dqurl0zr01"
      },
      "msg": "OK"
    },
    {
      "status": 200,
      "server_time": "2023-12-26 08:05:13",
      "msg": "OK",
      "result": {
        "filecode": "jledo3stkelm",
        "download_url": "https://ds2video.com/d/jledo3stkelm",
        "protected_download": "https://ds2video.com/d/guz80p07ymf19uzy7h26gqcttuo1f7vl",
        "protected_embed": "https://ds2video.com/e/gsujieuzi5yi1zpunok1fmrzmhpinn89",
        "embed_url": "https://ds2video.com/e/jledo3stkelm"
      }
    },
    {
      "server_time": "2023-12-26 08:05:13",
      "status": 200,
      "result": {
        "protected_download": "https://ds2video.com/d/8avdp98ulujx1bu0d3b75m9k8x7j3n18",
        "download_url": "https://ds2video.com/d/229a3lfgoq19",
        "filecode": "229a3lfgoq19",
        "embed_url": "https://ds2video.com/e/229a3lfgoq19",
        "protected_embed": "https://ds2video.com/e/zdy4ffmzs4ko6afrh6wb0b3pgo1bg562"
      },
      "msg": "OK"
    },
    {
      "msg": "OK",
      "result": {
        "embed_url": "https://ds2video.com/e/ygs95eddph9n",
        "protected_embed": "https://ds2video.com/e/l45yvck42koo756izu0rhxthyj0tnzja",
        "download_url": "https://ds2video.com/d/ygs95eddph9n",
        "protected_download": "https://ds2video.com/d/8nd0wgzpzmv5c4kcy02is298ekjvysee",
        "filecode": "ygs95eddph9n"
      },
      "server_time": "2023-12-26 08:05:13",
      "status": 200
    },
    {
      "status": 200,
      "server_time": "2023-12-26 08:05:14",
      "msg": "OK",
      "result": {
        "protected_download": "https://ds2video.com/d/v5s24j0ft2jxnx2nk59a4g9eod4qlmwb",
        "protected_embed": "https://ds2video.com/e/t0x56pf6unbgmza5956rg552v3cmfd62",
        "filecode": "fqx9lr2wx9fc",
        "download_url": "https://ds2video.com/d/fqx9lr2wx9fc",
        "embed_url": "https://ds2video.com/e/fqx9lr2wx9fc"
      }
    },
    {
      "status": 200,
      "server_time": "2023-12-26 08:05:14",
      "msg": "OK",
      "result": {
        "protected_download": "https://ds2video.com/d/mv49q6h907eujitl2gd74w25zhldlp4k",
        "download_url": "https://ds2video.com/d/ouevc17y97vs",
        "filecode": "ouevc17y97vs",
        "embed_url": "https://ds2video.com/e/ouevc17y97vs",
        "protected_embed": "https://ds2video.com/e/ogetb6qaor5utujm5qjo2c1kew9ittyj"
      }
    },
    {
      "msg": "OK",
      "server_time": "2023-12-26 08:05:15",
      "result": {
        "protected_embed": "https://ds2video.com/e/qzgcgi2xd9wx6ovop0n6ndmdhcuvwogu",
        "download_url": "https://ds2video.com/d/5ji6x8gycswd",
        "protected_download": "https://ds2video.com/d/28ey8fh2yet2pewojat3vj7w6romrpd0",
        "embed_url": "https://ds2video.com/e/5ji6x8gycswd",
        "filecode": "5ji6x8gycswd"
      },
      "status": 200
    },
    {
      "result": {
        "filecode": "cqhczqlh02ex",
        "embed_url": "https://ds2video.com/e/cqhczqlh02ex",
        "protected_embed": "https://ds2video.com/e/fnqrzne54l6xpfpoyombm3s49re35fdv",
        "protected_download": "https://ds2video.com/d/l5h24f3dmloltqvt2sklf7zya97uha2x",
        "download_url": "https://ds2video.com/d/cqhczqlh02ex"
      },
      "status": 200,
      "server_time": "2023-12-26 08:05:15",
      "msg": "OK"
    },
    {
      "status": 200,
      "result": {
        "filecode": "i57signodhfc",
        "protected_embed": "https://ds2video.com/e/kgjrd9ezx3nt6cdoedzmslfugtfced6o",
        "embed_url": "https://ds2video.com/e/i57signodhfc",
        "download_url": "https://ds2video.com/d/i57signodhfc",
        "protected_download": "https://ds2video.com/d/ye412tfvb6bhx7d1k4rln8pnadgjrogh"
      },
      "msg": "OK",
      "server_time": "2023-12-26 08:05:15"
    },
    {
      "result": {
        "download_url": "https://ds2video.com/d/3vapuwyzbwz8",
        "protected_download": "https://ds2video.com/d/9wduivrms8q9zj6cloon4aj7kjvffknl",
        "filecode": "3vapuwyzbwz8",
        "protected_embed": "https://ds2video.com/e/gl8bnytgn5oqlqm4gmlxe7cow4nswbdj",
        "embed_url": "https://ds2video.com/e/3vapuwyzbwz8"
      },
      "status": 200,
      "server_time": "2023-12-26 08:05:16",
      "msg": "OK"
    },
    {
      "msg": "OK",
      "result": {
        "download_url": "https://ds2video.com/d/z2hgy7m8gg46",
        "protected_download": "https://ds2video.com/d/h3jknlbv5yysw03vejdtyuzfgg9pwnfl",
        "filecode": "z2hgy7m8gg46",
        "embed_url": "https://ds2video.com/e/z2hgy7m8gg46",
        "protected_embed": "https://ds2video.com/e/pdzxiy4cj18v9i5yrp26199se76fqb3l"
      },
      "server_time": "2023-12-26 08:05:16",
      "status": 200
    },
    {
      "status": 200,
      "result": {
        "download_url": "https://ds2video.com/d/jl7ie8hgio7n",
        "protected_download": "https://ds2video.com/d/xqdmahhmrl0wjhy2k6ft2fgrpgp565f9",
        "protected_embed": "https://ds2video.com/e/8bw6mt542dk335fxcfoxz9p8e0bkekw7",
        "embed_url": "https://ds2video.com/e/jl7ie8hgio7n",
        "filecode": "jl7ie8hgio7n"
      },
      "msg": "OK",
      "server_time": "2023-12-26 08:05:16"
    },
    {
      "result": {
        "protected_download": "https://ds2video.com/d/8s02hvt0ie9osawdbs765std4w91a9qs",
        "download_url": "https://ds2video.com/d/9k5o9fm5965r",
        "filecode": "9k5o9fm5965r",
        "embed_url": "https://ds2video.com/e/9k5o9fm5965r",
        "protected_embed": "https://ds2video.com/e/1hvtr159twec8e2bbqhc6dgfg8r5gh1b"
      },
      "status": 200,
      "server_time": "2023-12-26 08:05:17",
      "msg": "OK"
    },
    {
      "result": {
        "protected_download": "https://ds2video.com/d/ce149pig94390r3oznkcnuyl5hm03i7b",
        "protected_embed": "https://ds2video.com/e/utubn2cyyhz5pq1q5a139172msd24xdc",
        "filecode": "w1oi5b367yy3",
        "embed_url": "https://ds2video.com/e/w1oi5b367yy3",
        "download_url": "https://ds2video.com/d/w1oi5b367yy3"
      },
      "server_time": "2023-12-26 08:05:17",
      "msg": "OK",
      "status": 200
    },
    {
      "server_time": "2023-12-26 08:05:17",
      "result": {
        "protected_download": "https://ds2video.com/d/vm5iaqzx9v0dl81q3baixyx2r6ml8414",
        "filecode": "l65a7xgnoj2t",
        "download_url": "https://ds2video.com/d/l65a7xgnoj2t",
        "protected_embed": "https://ds2video.com/e/921qf0itv3fx76zo36yoj3b89wp5mwpy",
        "embed_url": "https://ds2video.com/e/l65a7xgnoj2t"
      },
      "status": 200,
      "msg": "OK"
    },
    {
      "server_time": "2023-12-26 08:05:18",
      "msg": "OK",
      "status": 200,
      "result": {
        "protected_embed": "https://ds2video.com/e/imx0rryknpz8oo7ursyn8swbv8ujrqq4",
        "download_url": "https://ds2video.com/d/sb9fsiy0bir8",
        "embed_url": "https://ds2video.com/e/sb9fsiy0bir8",
        "protected_download": "https://ds2video.com/d/wv5e5ya3ykhyn90tmop87tfibcmjfh5e",
        "filecode": "sb9fsiy0bir8"
      }
    },
    {
      "msg": "OK",
      "status": 200,
      "server_time": "2023-12-26 08:05:18",
      "result": {
        "protected_download": "https://ds2video.com/d/1kh1rsb85dg0qjz3clgmff0rt69scrie",
        "protected_embed": "https://ds2video.com/e/ps3h8po64s3q63ziu40i1c5q8ds6v5bv",
        "filecode": "wbfdvhx964pk",
        "download_url": "https://ds2video.com/d/wbfdvhx964pk",
        "embed_url": "https://ds2video.com/e/wbfdvhx964pk"
      }
    },
    {
      "msg": "OK",
      "result": {
        "embed_url": "https://ds2video.com/e/2tq1zhrfb4si",
        "protected_download": "https://ds2video.com/d/x53xx5vx3cfi88dbw88zi70bos3xo952",
        "filecode": "2tq1zhrfb4si",
        "download_url": "https://ds2video.com/d/2tq1zhrfb4si",
        "protected_embed": "https://ds2video.com/e/2qaz589bb67d7yhcsv6gvjc5llcn4zsd"
      },
      "status": 200,
      "server_time": "2023-12-26 08:05:18"
    },
    {
      "server_time": "2023-12-26 08:05:19",
      "status": 200,
      "result": {
        "protected_embed": "https://ds2video.com/e/5l0hf1ab362r8bykmpyozwaq34jpumhr",
        "download_url": "https://ds2video.com/d/jvgy9pq0tq5s",
        "embed_url": "https://ds2video.com/e/jvgy9pq0tq5s",
        "protected_download": "https://ds2video.com/d/picn70hzuxyng2vlu4fbm5vzpituza1g",
        "filecode": "jvgy9pq0tq5s"
      },
      "msg": "OK"
    },
    {
      "status": 200,
      "result": {
        "embed_url": "https://ds2video.com/e/qhvm2fg68lz1",
        "download_url": "https://ds2video.com/d/qhvm2fg68lz1",
        "protected_embed": "https://ds2video.com/e/oca8dra473ki09oygmo30v8kzqnttykx",
        "filecode": "qhvm2fg68lz1",
        "protected_download": "https://ds2video.com/d/mliffxdmjn2ud19psx7g3wyovo7b11ap"
      },
      "msg": "OK",
      "server_time": "2023-12-26 08:05:19"
    },
    {
      "server_time": "2023-12-26 08:05:19",
      "msg": "OK",
      "result": {
        "protected_download": "https://ds2video.com/d/t04dohob265okqmjxek14mie9cju1h2q",
        "filecode": "tbar02waz8v4",
        "protected_embed": "https://ds2video.com/e/i86n8jgffvyvbz3wkg1yfgqgcagd3m5d",
        "download_url": "https://ds2video.com/d/tbar02waz8v4",
        "embed_url": "https://ds2video.com/e/tbar02waz8v4"
      },
      "status": 200
    },
    {
      "server_time": "2023-12-26 08:05:20",
      "msg": "OK",
      "status": 200,
      "result": {
        "filecode": "utssbn6yuyzw",
        "protected_download": "https://ds2video.com/d/lxmk84aw2zny52lj6lx2884r3zbxmn0z",
        "download_url": "https://ds2video.com/d/utssbn6yuyzw",
        "protected_embed": "https://ds2video.com/e/5upses5re6fp7v4x7m4rsz404gxbihz6",
        "embed_url": "https://ds2video.com/e/utssbn6yuyzw"
      }
    },
    {
      "result": {
        "protected_download": "https://ds2video.com/d/yq3ziodugxleojfmxvje5dx4js9o4foa",
        "protected_embed": "https://ds2video.com/e/l1hljbdbgm791h6z6xfi0npxzs1cc7al",
        "embed_url": "https://ds2video.com/e/i3m2olch6aih",
        "download_url": "https://ds2video.com/d/i3m2olch6aih",
        "filecode": "i3m2olch6aih"
      },
      "server_time": "2023-12-26 08:05:20",
      "msg": "OK",
      "status": 200
    },
    {
      "status": 200,
      "result": {
        "filecode": "uzxojxszzvi7",
        "protected_download": "https://ds2video.com/d/tu7vb9cjd6yzeodw36y22tmvyk3j9nye",
        "embed_url": "https://ds2video.com/e/uzxojxszzvi7",
        "download_url": "https://ds2video.com/d/uzxojxszzvi7",
        "protected_embed": "https://ds2video.com/e/xpbzuf2bvfso7mpyfaqq5npf8fvbiq8m"
      },
      "msg": "OK",
      "server_time": "2023-12-26 08:05:20"
    },
    {
      "result": {
        "protected_embed": "https://ds2video.com/e/gk5j8iubsd1bc11m9n7d39eopl65dsfx",
        "download_url": "https://ds2video.com/d/9k6t7lzlngd3",
        "filecode": "9k6t7lzlngd3",
        "protected_download": "https://ds2video.com/d/46rd3u934ihbizvjfjd3701ci4ivxrix",
        "embed_url": "https://ds2video.com/e/9k6t7lzlngd3"
      },
      "status": 200,
      "server_time": "2023-12-26 08:05:21",
      "msg": "OK"
    },
    {
      "server_time": "2023-12-26 08:05:21",
      "status": 200,
      "result": {
        "download_url": "https://ds2video.com/d/k85drlholb4n",
        "filecode": "k85drlholb4n",
        "protected_download": "https://ds2video.com/d/y6x9fuygnofwuxckssf0ibet89m4y7hz",
        "embed_url": "https://ds2video.com/e/k85drlholb4n",
        "protected_embed": "https://ds2video.com/e/s1hzjlzt3vt9pau38kkcbsnmrs91ufy5"
      },
      "msg": "OK"
    },
    {
      "status": 200,
      "msg": "OK",
      "server_time": "2023-12-26 08:05:21",
      "result": {
        "embed_url": "https://ds2video.com/e/k8f1od7017ew",
        "download_url": "https://ds2video.com/d/k8f1od7017ew",
        "filecode": "k8f1od7017ew",
        "protected_embed": "https://ds2video.com/e/ovp2ojr1xf6hhu3icwxo0ijjegl8eij4",
        "protected_download": "https://ds2video.com/d/tpsmupgbeet8ji050adgq55tz8egbguz"
      }
    },
    {
      "status": 200,
      "msg": "OK",
      "server_time": "2023-12-26 08:05:22",
      "result": {
        "download_url": "https://ds2video.com/d/1jvhebnjq2gq",
        "embed_url": "https://ds2video.com/e/1jvhebnjq2gq",
        "protected_embed": "https://ds2video.com/e/qk2uyhnemgb8d138xotd5ol152pg6m36",
        "filecode": "1jvhebnjq2gq",
        "protected_download": "https://ds2video.com/d/9bsv3bg8hof6lk37ilokhxshy02ov5u2"
      }
    },
    {
      "status": 200,
      "msg": "OK",
      "server_time": "2023-12-26 08:05:22",
      "result": {
        "embed_url": "https://ds2video.com/e/61s7slt4brh0",
        "download_url": "https://ds2video.com/d/61s7slt4brh0",
        "filecode": "61s7slt4brh0",
        "protected_download": "https://ds2video.com/d/1eax3b5qmbny77epa7rbmfdylos53osp",
        "protected_embed": "https://ds2video.com/e/8pqjeihxjjjd993i0g9z7ll7vnyksfyi"
      }
    },
    {
      "server_time": "2023-12-26 08:05:22",
      "msg": "OK",
      "result": {
        "protected_download": "https://ds2video.com/d/dkwmvuicbtdg92mmp6ntnsv47tg7g1f8",
        "download_url": "https://ds2video.com/d/gbdfw3w7qeq7",
        "filecode": "gbdfw3w7qeq7",
        "protected_embed": "https://ds2video.com/e/8t2i6gwrwnqt2vrcngdkwjgagy3zs2pw",
        "embed_url": "https://ds2video.com/e/gbdfw3w7qeq7"
      },
      "status": 200
    },
    {
      "server_time": "2023-12-26 08:05:23",
      "msg": "OK",
      "status": 200,
      "result": {
        "download_url": "https://ds2video.com/d/87ok4ut0bxe5",
        "embed_url": "https://ds2video.com/e/87ok4ut0bxe5",
        "protected_embed": "https://ds2video.com/e/iecb926vfc4yrnrj7rt4d2mt6jzhm2fs",
        "protected_download": "https://ds2video.com/d/asl5p07by2h8nktboqm8hfhnk73s1fe6",
        "filecode": "87ok4ut0bxe5"
      }
    },
    {
      "msg": "OK",
      "result": {
        "protected_embed": "https://ds2video.com/e/koj7j0hijpfb1ten7atxmmdvr0ejs3r8",
        "embed_url": "https://ds2video.com/e/qr4l85fvl5vg",
        "filecode": "qr4l85fvl5vg",
        "protected_download": "https://ds2video.com/d/fh6gq52xwaf68yytvfmuom708nc3ahq3",
        "download_url": "https://ds2video.com/d/qr4l85fvl5vg"
      },
      "status": 200,
      "server_time": "2023-12-26 08:05:23"
    },
    {
      "server_time": "2023-12-26 08:05:23",
      "result": {
        "filecode": "fby9njrs37rt",
        "protected_embed": "https://ds2video.com/e/ekio5qo6t8de6v89q30riq68yvken8uo",
        "protected_download": "https://ds2video.com/d/cde8q2wysa33zlnv8pmd5u1q8tmlu1sj",
        "embed_url": "https://ds2video.com/e/fby9njrs37rt",
        "download_url": "https://ds2video.com/d/fby9njrs37rt"
      },
      "msg": "OK",
      "status": 200
    },
    {
      "server_time": "2023-12-26 08:05:24",
      "result": {
        "download_url": "https://ds2video.com/d/i1sb9erm4qup",
        "embed_url": "https://ds2video.com/e/i1sb9erm4qup",
        "protected_download": "https://ds2video.com/d/cu9a53w6c3y9fjcow8ssn5c387ijb5pw",
        "protected_embed": "https://ds2video.com/e/2qffk0jkndmlznsvdefpxf4lblqkyhuc",
        "filecode": "i1sb9erm4qup"
      },
      "msg": "OK",
      "status": 200
    },
    {
      "result": {
        "download_url": "https://ds2video.com/d/mueouruf2n8k",
        "filecode": "mueouruf2n8k",
        "embed_url": "https://ds2video.com/e/mueouruf2n8k",
        "protected_embed": "https://ds2video.com/e/hly8hknwbncoqbp13grpv81pyy126yjv",
        "protected_download": "https://ds2video.com/d/eisl502y0m7iam40frbtv2b7tt3uj0ea"
      },
      "msg": "OK",
      "status": 200,
      "server_time": "2023-12-26 08:05:24"
    },
    {
      "result": {
        "protected_download": "https://ds2video.com/d/5wa9wd6mkrmuftkbsroes3nu0b8hfke6",
        "protected_embed": "https://ds2video.com/e/vs8th39z6k25ph14glvzuhcsswtvy2pn",
        "embed_url": "https://ds2video.com/e/2pieqdl1l2rs",
        "download_url": "https://ds2video.com/d/2pieqdl1l2rs",
        "filecode": "2pieqdl1l2rs"
      },
      "msg": "OK",
      "status": 200,
      "server_time": "2023-12-26 08:05:25"
    },
    {
      "result": {
        "protected_embed": "https://ds2video.com/e/e9bzceww9d1f49264nqkqqygl1mhh6mv",
        "embed_url": "https://ds2video.com/e/cmy5gcma6dlk",
        "filecode": "cmy5gcma6dlk",
        "download_url": "https://ds2video.com/d/cmy5gcma6dlk",
        "protected_download": "https://ds2video.com/d/lndd42sol4za3wlnr3lpwg9htb0gsndn"
      },
      "status": 200,
      "server_time": "2023-12-26 08:05:25",
      "msg": "OK"
    },
    {
      "msg": "OK",
      "result": {
        "protected_embed": "https://ds2video.com/e/8o3zgck8xbez14mlm1s3rqxnc5b8m8mi",
        "protected_download": "https://ds2video.com/d/7dt065ydkxnjz2phx9jf20w22hlyuw8s",
        "filecode": "fpppnicotcy6",
        "embed_url": "https://ds2video.com/e/fpppnicotcy6",
        "download_url": "https://ds2video.com/d/fpppnicotcy6"
      },
      "status": 200,
      "server_time": "2023-12-26 08:05:25"
    },
    {
      "server_time": "2023-12-26 08:05:26",
      "result": {
        "protected_embed": "https://ds2video.com/e/cy7b07mglr9jqzdycvgb0w3njggl5fa5",
        "protected_download": "https://ds2video.com/d/q3ek40krgfqqd7i1qa9s10po3irahtxa",
        "filecode": "9y9ufejw7j4e",
        "embed_url": "https://ds2video.com/e/9y9ufejw7j4e",
        "download_url": "https://ds2video.com/d/9y9ufejw7j4e"
      },
      "status": 200,
      "msg": "OK"
    }
  ]
}